{
  "chapterId": "chapter23",
  "mode": "revision",
  "iteration": 3,
  "feedbackPath": ".afternoon/chapters/chapter23/grounding-gate-notes-r2.json",
  "targetFile": "v2g-r2.md",
  "globalRisks": [
    "combat-cold drifting into atmospheric metaphor",
    "spell-timing beats slipping into mechanism summary",
    "final-third soul-echo and blade-state abstraction"
  ],
  "touchedScenes": [
    "Scene 2 - The Murder",
    "Scene 3 - The Fight",
    "Scene 4 - The Aftermath"
  ],
  "sceneAudits": [
    {
      "scene": "Scene 2 - The Murder",
      "biggestGap": "The first live combat turn let chamber cold drift toward atmospheric mood instead of staying with breath, blood, and light on the seal.",
      "anchorsAdded": {
        "place": [
          "high window",
          "golden seal"
        ],
        "material": [
          "iced king's blood",
          "stinging breath"
        ],
        "dialogue": [
          "reveal exchange kept against the seal and the turning room"
        ],
        "exit": [
          "Arthas turning back from Terenas toward them"
        ]
      },
      "dialogueGroundingApplied": true,
      "finalBeatChecked": true
    },
    {
      "scene": "Scene 3 - The Fight",
      "biggestGap": "Several spell beats still named theory or timing in summary instead of cashing them out through blade-note, footing, cracked marble, and the back-turned second Jaina needs.",
      "anchorsAdded": {
        "place": [
          "marble under the columns",
          "the seal",
          "the space behind Arthas's back"
        ],
        "material": [
          "caught note in the blade",
          "cracking marble",
          "slip of footing"
        ],
        "dialogue": [
          "combat beats left pinned to Sylvanas's bodily cost and Arthas's turn"
        ],
        "exit": [
          "one breath with his back turned"
        ]
      },
      "dialogueGroundingApplied": true,
      "finalBeatChecked": true
    },
    {
      "scene": "Scene 4 - The Aftermath",
      "biggestGap": "The soul-echo and wounded-blade aftermath risked drifting into neat explanation instead of staying fragmentary, painful, and physically manifest on the marble.",
      "anchorsAdded": {
        "place": [
          "steps beneath the throne",
          "marble under the sword"
        ],
        "material": [
          "memory fragments only",
          "crack near the seam",
          "light leaking through the blade",
          "hilt twitch on marble"
        ],
        "dialogue": [
          "warning to leave the blade untouched stays tied to Sylvanas's visible wound state"
        ],
        "exit": [
          "wounded note answering on the marble before witnesses close the room"
        ]
      },
      "dialogueGroundingApplied": true,
      "finalBeatChecked": true
    }
  ],
  "finalThirdAudit": {
    "risksFound": [
      "sentimental overreach in the soul-echo close",
      "anthropomorphic summary in the blade-state beat",
      "fight-mechanism phrasing lingering too close to workshop shorthand"
    ],
    "fixesApplied": [
      "cut the last neat boyhood vignette and left the soul-echo fragmentary",
      "rebound Frostmourne's post-cast state to crack, note-snag, light leak, and marble contact",
      "replaced summary timing lines with breath, footing, blood, and room-specific pressure"
    ],
    "residualConcerns": []
  },
  "sourceAudit": {
    "memoryFiles": [
      "relationships/cyndia--jaina",
      "locations/lordaerons-palace",
      "characters/uther",
      "relationships/arthas--jaina",
      "characters/arthas-menethil",
      "relationships/jaina--sylvanas",
      "threads/frostmourne-seam-weakness",
      "relationships/arthas--sylvanas",
      "threads/anti-blade-palace-confrontation"
    ],
    "materials": [
      ".afternoon/plans/chapter23.json",
      "stories/the-plague-road/plans/story-arc.md",
      "stories/the-plague-road/characters/voice-sheets/jaina-voice.md",
      "stories/the-plague-road/characters/voice-sheets/sylvanas-voice.md",
      ".afternoon/style-guide.json"
    ],
    "unsourcedAdditions": []
  }
}
